pyqubes
