Metadata-Version: 1.1
Name: pyqubes
Version: 0.0.3
Summary: QubesOS dom0 automation in Python
Home-page: https://github.com/tommilligan/pyqubes/
Author: Tom Milligan
Author-email: code@tommilligan.net
License: Apache License 2.0
Keywords: qubes qubesos QubesOS wrapper recipe dom0 vm templatevm appvm
Platform: any
Classifier: Programming Language :: Python :: 2
Classifier: Programming Language :: Python :: 2.7
Classifier: Programming Language :: Python :: 3
Classifier: Programming Language :: Python :: 3.2
Classifier: Programming Language :: Python :: 3.3
Classifier: Programming Language :: Python :: 3.4
Classifier: Programming Language :: Python :: 3.5
Classifier: Programming Language :: Python :: 3.6
Classifier: License :: OSI Approved :: Apache Software License
Classifier: Operating System :: POSIX :: Linux
Classifier: Development Status :: 3 - Alpha
Classifier: Intended Audience :: Developers
Classifier: Intended Audience :: End Users/Desktop
Classifier: Natural Language :: English
Classifier: Topic :: Desktop Environment
Classifier: Topic :: System :: Installation/Setup
